client/__init__.py
client/client.py
client/decorators.py
client/errors.py
client/client/__init__.py
client/client/add_contact.py
client/client/client_db_storage.py
client/client/delete_contact.py
client/client/main_window.py
client/client/main_window_conv.py
client/client/start_window.py
client/client/transport.py
kaa_mess_client-0.0.1.dist-info/METADATA
kaa_mess_client-0.0.1.dist-info/WHEEL
kaa_mess_client-0.0.1.dist-info/top_level.txt
kaa_mess_client-0.0.1.dist-info/RECORD
