Metadata-Version: 2.1
Name: kaa-mess-client
Version: 0.0.1
Summary: messanger_client
Home-page: UNKNOWN
Author: KAA
Author-email: kaa@gmail.com
License: UNKNOWN
Platform: UNKNOWN
Requires-Dist: PyQt5
Requires-Dist: sqlalchemy
Requires-Dist: pycryptodome
Requires-Dist: pycryptodomex
